pyjon.descriptors-1.7.7-py3.4-nspkg.pth
pyjon/descriptors/main.py
pyjon/descriptors/readers.py
pyjon/descriptors/__init__.py
pyjon/descriptors/exceptions.py
pyjon/descriptors/input.py
pyjon/descriptors/tests/test_casters.py
pyjon/descriptors/tests/test_inputitem.py
pyjon/descriptors/tests/test_itemfactory.py
pyjon/descriptors/tests/__init__.py
pyjon/descriptors/tests/test_xmlreader.py
pyjon/descriptors/tests/test_utils.py
pyjon/descriptors/tests/test_readers.py
pyjon/descriptors/tests/test_descriptor.py
pyjon/descriptors/casters/main.py
pyjon/descriptors/casters/__init__.py
pyjon.descriptors-1.7.7.dist-info/DESCRIPTION.rst
pyjon.descriptors-1.7.7.dist-info/top_level.txt
pyjon.descriptors-1.7.7.dist-info/METADATA
pyjon.descriptors-1.7.7.dist-info/RECORD
pyjon.descriptors-1.7.7.dist-info/WHEEL
pyjon.descriptors-1.7.7.dist-info/metadata.json
pyjon.descriptors-1.7.7.dist-info/namespace_packages.txt
pyjon.descriptors-1.7.7.dist-info/entry_points.txt
