Metadata-Version: 1.1
Name: pyjon.descriptors
Version: 1.7.7
Summary: Provides a system of descriptors to read files and return objects
Home-page: https://bitbucket.org/xcg/pyjon.descriptors
Author: Florent Aide, Jerome Collette, Jonathan Schemoul
Author-email: florent.aide@gmail.com, collette.jerome@gmail.com, jonathan.schemoul@gmail.com
License: MIT
Platform: UNKNOWN
Classifier: Programming Language :: Python
Classifier: Topic :: Text Processing
Classifier: Topic :: Software Development :: Libraries :: Python Modules
Classifier: License :: OSI Approved :: MIT License
